MANIFEST.in
setup.py
bin/panama
panama/__init__.py
panama.egg-info/PKG-INFO
panama.egg-info/SOURCES.txt
panama.egg-info/dependency_links.txt
panama.egg-info/requires.txt
panama.egg-info/top_level.txt
panama/core/lmm/c_lmm.cpp
panama/core/lmm/lmm.cpp
panama/core/lmm/utils/Beta.cpp
panama/core/lmm/utils/BrentC.cpp
panama/core/lmm/utils/FisherF.cpp
panama/core/lmm/utils/Gamma.cpp
panama/core/lmm/utils/MathFunctions.cpp
panama/core/__init__.py
panama/core/confounders.py
panama/core/qvalue.py
panama/core/testing.py
panama/core/testing_core.py
panama/core/lmm/__init__.py
panama/core/lmm/c_lmm.cpp
panama/core/lmm/lmm.cpp
panama/core/lmm/lmm.h
panama/core/lmm/lmm.pyx
panama/core/lmm/lmm_fast.py
panama/core/lmm/lmm_fast_old.py
panama/core/lmm/lmm_slow.py
panama/core/lmm/setup.py
panama/core/lmm/test_lmm.py
panama/core/lmm/Eigen/Array
panama/core/lmm/Eigen/CMakeLists.txt
panama/core/lmm/Eigen/Cholesky
panama/core/lmm/Eigen/CholmodSupport
panama/core/lmm/Eigen/Core
panama/core/lmm/Eigen/Dense
panama/core/lmm/Eigen/Eigen
panama/core/lmm/Eigen/Eigen2Support
panama/core/lmm/Eigen/Eigenvalues
panama/core/lmm/Eigen/Geometry
panama/core/lmm/Eigen/Householder
panama/core/lmm/Eigen/IterativeLinearSolvers
panama/core/lmm/Eigen/Jacobi
panama/core/lmm/Eigen/LU
panama/core/lmm/Eigen/LeastSquares
panama/core/lmm/Eigen/OrderingMethods
panama/core/lmm/Eigen/PARDISOSupport
panama/core/lmm/Eigen/QR
panama/core/lmm/Eigen/QtAlignedMalloc
panama/core/lmm/Eigen/SVD
panama/core/lmm/Eigen/Sparse
panama/core/lmm/Eigen/SparseCholesky
panama/core/lmm/Eigen/SparseCore
panama/core/lmm/Eigen/StdDeque
panama/core/lmm/Eigen/StdList
panama/core/lmm/Eigen/StdVector
panama/core/lmm/Eigen/SuperLUSupport
panama/core/lmm/Eigen/UmfPackSupport
panama/core/lmm/Eigen/src/CMakeLists.txt
panama/core/lmm/Eigen/src/Cholesky/CMakeLists.txt
panama/core/lmm/Eigen/src/Cholesky/LDLT.h
panama/core/lmm/Eigen/src/Cholesky/LLT.h
panama/core/lmm/Eigen/src/Cholesky/LLT_MKL.h
panama/core/lmm/Eigen/src/CholmodSupport/CMakeLists.txt
panama/core/lmm/Eigen/src/CholmodSupport/CholmodSupport.h
panama/core/lmm/Eigen/src/Core/Array.h
panama/core/lmm/Eigen/src/Core/ArrayBase.h
