Metadata-Version: 1.0
Name: panama
Version: 0.58
Summary: a novel probabilistic model to account for confounding factors in eQTL studies
Home-page: http://ml.sheffield.ac.uk/qtl/panama/
Author: Nicolo Fusi*, Oliver Stegle*, Neil Lawrence
Author-email: nicolo.fusi@sheffield.ac.uk
License: BSD
Platform: UNKNOWN
